{"type": "FeatureCollection", "features": [{"type": "Feature", "geometry": {"type": "Point", "coordinates": [2.3518277777778, 48.856577777778]}, "properties": {"description": "Paris", "name": "Paris"}}, {"type": "Feature", "geometry": {"type": "Point", "coordinates": [3.175, 42.263333]}, "properties": {"description": "Roses", "name": "Roses"}}, {"type": "Feature", "geometry": {"type": "Point", "coordinates": [0.63333333333333, 41.616666666667]}, "properties": {"description": "Lleida", "name": "Lleida"}}, {"type": "Feature", "geometry": {"type": "Point", "coordinates": [1.2494444444444, 41.115555555556]}, "properties": {"description": "Tarragona", "name": "Tarragona"}}], "crs": {"type": "name", "properties": {"name": "urn:ogc:def:crs:OGC:2:84"}}, "bbox": [0.63333333333333, 0.63333333333333, 48.856577777778, 48.856577777778]}