{"type": "FeatureCollection", "features": [{"type": "Feature", "geometry": {"type": "Point", "coordinates": [23.583333333333, 46.766666666667]}, "properties": {"description": "Transsylvanien", "name": "Transsylvanien"}}, {"type": "Feature", "geometry": {"type": "Point", "coordinates": [16.608333333333, 49.195277777778]}, "properties": {"description": "Brno", "name": "Brno"}}, {"type": "Feature", "geometry": {"type": "Point", "coordinates": [16.373064, 48.20833]}, "properties": {"description": "Wien", "name": "Wien"}}, {"type": "Feature", "geometry": {"type": "Point", "coordinates": [29.647293, 45.16291]}, "properties": {"description": "Donau", "name": "Donau"}}, {"type": "Feature", "geometry": {"type": "Point", "coordinates": [16.566666666667, 48.566666666667]}, "properties": {"description": "Mistelbach", "name": "Mistelbach"}}], "crs": {"type": "name", "properties": {"name": "urn:ogc:def:crs:OGC:2:84"}}, "bbox": [16.373064, 16.373064, 48.566666666667, 48.566666666667]}